khmerocr_tools/__init__.py
khmerocr_tools/src/__init__.py
khmerocr_tools/src/khmerocr_tools.py
khmerocr_tools-0.13.dist-info/LICENSE.txt
khmerocr_tools-0.13.dist-info/METADATA
khmerocr_tools-0.13.dist-info/WHEEL
khmerocr_tools-0.13.dist-info/top_level.txt
khmerocr_tools-0.13.dist-info/RECORD
