Metadata-Version: 2.1
Name: khmerocr-tools
Version: 0.13
Summary: Khmerocr_tools is a Python library that generates synthetic images containing Khmer text
Home-page: https://github.com/MetythornPenn/khmerocr_tools
Author: Metythorn Penn
Author-email: Metythorn@gmail.com
License: MIT
Classifier: License :: OSI Approved :: MIT License
Classifier: Programming Language :: Python :: 3.10
Classifier: Operating System :: OS Independent
Requires-Python: >=3.8
License-File: LICENSE.txt
Requires-Dist: Pillow >=10.2.0
